{
	"stone" : 	{
		"container" : "meta/organ.maxpat",
		"structs" : 		{

		}

	}
,
	"pine_tree" : 	{
		"container" : "meta/organ.maxpat",
		"structs" : 		{
			"trunk" : 			{
				"struct_file" : "meta/structs/pine_tree/trunk.maxpat",
				"enable" : 1,
				"init_amp" : 1
			}
,
			"branches" : 			{
				"struct_file" : "meta/structs/pine_tree/branches.maxpat",
				"enable" : 0,
				"init_amp" : 1
			}
,
			"roots" : 			{
				"struct_file" : "meta/structs/pine_tree/roots.maxpat",
				"enable" : 0,
				"init_amp" : 1
			}
,
			"cones" : 			{
				"struct_file" : "meta/structs/pine_tree/cones.maxpat",
				"enable" : 0,
				"init_amp" : 1
			}

		}

	}
,
	"player" : 	{
		"container" : "meta/organ.maxpat",
		"structs" : 		{
			"head" : 			{
				"struct_file" : "meta/structs/player/head.maxpat",
				"enable" : 1,
				"init_amp" : 0,
				"pan_offset" : [ 0.0, 0.0, 0.0 ]
			}
,
			"torso" : 			{
				"struct_file" : "meta/structs/player/torso.maxpat",
				"enable" : 0,
				"init_amp" : 0,
				"pan_offset" : [ -2.0, -1.0, 0.5 ]
			}
,
			"arms" : 			{
				"struct_file" : "meta/structs/player/arms.maxpat",
				"enable" : 0,
				"init_amp" : 0,
				"pan_offset" : [ 0.0, -0.5, 0.0 ]
			}
,
			"legs" : 			{
				"struct_file" : "meta/structs/player/legs.maxpat",
				"enable" : 0,
				"init_amp" : 0,
				"pan_offset" : [ 0.0, -1.5, 0.2 ]
			}

		}

	}

}
